loid/__init__.py
loid/cli.py
loid/constants/__init__.py
loid/constants/informations.py
loid/constants/services.py
loid/constants/system.py
loid/exceptions/__init__.py
loid/exceptions/system.py
loid/middlewares/__init__.py
loid/middlewares/hashnode.py
loid/scripts/__init__.py
loid/scripts/commentonpost.py
loid/scripts/createfile.py
loid/scripts/draftpostviewer.py
loid/scripts/fetchpublicationid.py
loid/scripts/fetchtagid.py
loid/scripts/getaianswer.py
loid/scripts/getdraft.py
loid/scripts/getfeed.py
loid/scripts/getpost.py
loid/scripts/getpublication.py
loid/scripts/listdrafts.py
loid/scripts/listonlinedrafts.py
loid/scripts/publishdraft.py
loid/scripts/publishonlinedrafts.py
loid/scripts/showtabledata.py
loid/scripts/texteditor.py
loid/scripts/uploadimages.py
loid-0.1.5.dist-info/LICENSE
loid-0.1.5.dist-info/METADATA
loid-0.1.5.dist-info/WHEEL
loid-0.1.5.dist-info/entry_points.txt
loid-0.1.5.dist-info/top_level.txt
loid-0.1.5.dist-info/RECORD
