Metadata-Version: 2.1
Name: loid
Version: 0.1.5
Summary: Read,Write and Publish from your terminal!.
Home-page: https://github.com/captain0jay/loid
Author: Captain Jay
Author-email: capja778@gmail.com
License: MIT
Keywords: loid
Platform: UNKNOWN
Classifier: Development Status :: 3 - Alpha
Classifier: Intended Audience :: Developers
Classifier: Intended Audience :: Education
Classifier: License :: OSI Approved :: MIT License
Classifier: Natural Language :: English
Classifier: Operating System :: POSIX
Classifier: Operating System :: Unix
Classifier: Programming Language :: Python :: 3
Classifier: Programming Language :: Python :: 3 :: Only
Classifier: Programming Language :: Python :: Implementation :: CPython
Classifier: Programming Language :: Python :: Implementation :: PyPy
Classifier: Topic :: Utilities
Requires-Python: >=3.7
License-File: LICENSE
Requires-Dist: keyring (>=23.5.0)
Requires-Dist: requests (>=2.25.1)
Requires-Dist: rich (>=13.7.0)
Requires-Dist: tabulate (>=0.9.0)
